{"1.0.0": {"last_update": 1596531806.70236, "gamepack": "game_pack_2020-08-04T17-03-20.574658.tar.zst", "updatepack": "game_patch_2020-08-05T00-41-11.125562.tar.zst"}, "0.1.1": {"last_update": 1596530647.265537, "gamepack": "/tpdl-client-download/game_pack_2020-08-04T16-44-00.682514.tar.zst", "updatepack": ""}, "0.1.0": {"last_update": 1596531653.92127, "gamepack": "game_pack_2020-08-04T17-00-47.749182.tar.zst", "updatepack": ""}, "0.01.0": {"last_update": 1596531238.21826, "gamepack": "/tpdl-client-download/game_pack_2020-08-04T16-53-52.716142.tar.zst", "updatepack": ""}, "1.0.1": {"last_update": 1596531897.572834, "gamepack": "game_pack_2020-08-04T17-04-51.687914.tar.zst", "updatepack": "game_patch_2020-08-04T17-11-52.161394.tar.zst"}, "1.0.2": {"last_update": 1596532311.954363, "gamepack": "game_pack_2020-08-04T17-11-45.768359.tar.zst", "updatepack": "game_patch_2020-08-04T20-39-27.826836.tar.zst"}, "1.0.3": {"last_update": 1596544767.606935, "gamepack": "game_pack_2020-08-04T20-39-21.863877.tar.zst", "updatepack": "game_patch_2020-08-04T23-40-35.803793.tar.zst"}, "1.0.4": {"last_update": 1596555635.588331, "gamepack": "game_pack_2020-08-04T23-40-29.554621.tar.zst", "updatepack": "game_patch_2020-08-05T00-41-10.556297.tar.zst"}, "1.0.5": {"last_update": 1596559270.26615, "gamepack": "game_pack_2020-08-05T00-41-04.489271.tar.zst", "updatepack": ""}}